MANIFEST.in
README.md
setup.py
pysster/Alphabet_Encoder.py
pysster/Data.py
pysster/Grid_Search.py
pysster/Model.py
pysster/Motif.py
pysster/One_Hot_Encoder.py
pysster/__init__.py
pysster/utils.py
pysster.egg-info/PKG-INFO
pysster.egg-info/SOURCES.txt
pysster.egg-info/dependency_links.txt
pysster.egg-info/not-zip-safe
pysster.egg-info/requires.txt
pysster.egg-info/top_level.txt
pysster/resources/motif/LiberationSans-Regular.ttf
pysster/resources/motif/char(.png
pysster/resources/motif/char).png
pysster/resources/motif/char,.png
pysster/resources/motif/char..png
pysster/resources/motif/char0.png
pysster/resources/motif/char1.png
pysster/resources/motif/char2.png
pysster/resources/motif/char3.png
pysster/resources/motif/char4.png
pysster/resources/motif/char5.png
pysster/resources/motif/char6.png
pysster/resources/motif/char7.png
pysster/resources/motif/char8.png
pysster/resources/motif/char9.png
pysster/resources/motif/charA.png
pysster/resources/motif/charB.png
pysster/resources/motif/charC.png
pysster/resources/motif/charD.png
pysster/resources/motif/charE.png
pysster/resources/motif/charF.png
pysster/resources/motif/charG.png
pysster/resources/motif/charH.png
pysster/resources/motif/charI.png
pysster/resources/motif/charJ.png
pysster/resources/motif/charK.png
pysster/resources/motif/charL.png
pysster/resources/motif/charM.png
pysster/resources/motif/charN.png
pysster/resources/motif/charO.png
pysster/resources/motif/charP.png
pysster/resources/motif/charQ.png
pysster/resources/motif/charR.png
pysster/resources/motif/charS.png
pysster/resources/motif/charT.png
pysster/resources/motif/charU.png
pysster/resources/motif/charV.png
pysster/resources/motif/charW.png
pysster/resources/motif/charX.png
pysster/resources/motif/charY.png
pysster/resources/motif/charZ.png
pysster/resources/motif/char[.png
pysster/resources/motif/char].png
pysster/resources/motif/char_except0.png
pysster/resources/motif/char_except1.png
pysster/resources/motif/char_except2.png
pysster/resources/motif/char_except3.png
pysster/resources/motif/char{.png
pysster/resources/motif/char}.png