Metadata-Version: 1.2
Name: pysster
Version: 1.1.3
Summary: a Sequence/STructure classifiER for biological sequences
Home-page: https://github.com/budach/pysster
Author: Stefan Budach
Author-email: budach@molgen.mpg.de
License: MIT
Platform: UNKNOWN
Requires-Python: >=3.5
